Taowa_wx/__init__.py
Taowa_wx/wx界面.py
Taowa_wx-1.0.6.dist-info/METADATA
Taowa_wx-1.0.6.dist-info/WHEEL
Taowa_wx-1.0.6.dist-info/top_level.txt
Taowa_wx-1.0.6.dist-info/RECORD
