Metadata-Version: 2.1
Name: Taowa_wx
Version: 1.0.6
Summary: wxPython命令
Author: 
Author-email: 
Classifier: Programming Language :: Python :: 3
Classifier: License :: OSI Approved :: MIT License
Classifier: Operating System :: OS Independent
Requires-Python: >=3.6
Requires-Dist: wxPython
